setup.py
MI7.egg-info/PKG-INFO
MI7.egg-info/SOURCES.txt
MI7.egg-info/dependency_links.txt
MI7.egg-info/top_level.txt
mi7/__init__.py
mi7/core.py
mi7/errors.py
mi7/version.py