Metadata-Version: 1.0
Name: MI7
Version: 0.1.0
Summary: MI7 is a lightweight and fun spying test framework. It's
Home-page: https://github.com/heynemann/mi7/wiki
Author: Bernardo Heynemann
Author-email: heynemann@gmail.com
License: OSI
Keywords: Spy Test Framework Mock TDD
Platform: UNKNOWN
Classifier: Development Status :: 3 - Alpha
Classifier: Intended Audience :: Developers
Classifier: License :: OSI Approved
Classifier: Natural Language :: English
Classifier: Operating System :: MacOS
Classifier: Operating System :: Microsoft :: Windows
Classifier: Operating System :: POSIX :: Linux
Classifier: Programming Language :: Python :: 2.6
